bjoda/__init__.py
bjoda/globals.py
bjoda/strings.py
bjoda-0.0.4.dist-info/DESCRIPTION.rst
bjoda-0.0.4.dist-info/METADATA
bjoda-0.0.4.dist-info/RECORD
bjoda-0.0.4.dist-info/WHEEL
bjoda-0.0.4.dist-info/metadata.json
bjoda-0.0.4.dist-info/top_level.txt
