Metadata-Version: 2.0
Name: bjoda
Version: 0.0.4
Summary: Better syscalls and commands from python
Home-page: UNKNOWN
Author: Jacobi Petrucciani
Author-email: jacobi@mimirhq.com
License: UNKNOWN
Platform: Any
Classifier: Programming Language :: Python
Classifier: Programming Language :: Python :: 3
Classifier: Programming Language :: Python :: 3.3
Classifier: Programming Language :: Python :: 3.4
Classifier: Programming Language :: Python :: 3.5
Classifier: Programming Language :: Python :: 3.6
Classifier: Programming Language :: Python :: Implementation :: CPython
Classifier: Programming Language :: Python :: Implementation :: PyPy
Requires-Dist: pexpect (>=4.1.0)
